<!--

    Sonatype Nexus (TM) Open Source Version
    Copyright (c) 2008-present Sonatype, Inc.
    All rights reserved. Includes the third-party code listed at http://links.sonatype.com/products/nexus/oss/attributions.

    This program and the accompanying materials are made available under the terms of the Eclipse Public License Version 1.0,
    which accompanies this distribution and is available at http://www.eclipse.org/legal/epl-v10.html.

    Sonatype Nexus (TM) Professional Version is available from Sonatype, Inc. "Sonatype" and "Sonatype Nexus" are trademarks
    of Sonatype, Inc. Apache Maven is a trademark of the Apache Software Foundation. M2eclipse is a trademark of the
    Eclipse Foundation. All other trademarks are the property of their respective owners.

-->
<model xsd.namespace="http://www.sonatype.com/xsd/security-configuration-2.0.3"
       xsd.targetNamespace="http://www.sonatype.com/xsd/security-configuration-2.0.3">

  <id>security</id>

  <name>SecurityConfiguration</name>

  <description>
    <![CDATA[
      <p>XML Based Security Configuration.</p>
      ]]>
  </description>

  <defaults>
    <default>
      <key>package</key>
      <value>org.sonatype.security.configuration.model</value>
    </default>
  </defaults>

  <classes>

    <class rootElement="true" xml.tagName="security-configuration">
      <name>SecurityConfiguration</name>
      <version>2.0.3+</version>
      <interfaces>
        <interface>org.sonatype.configuration.Configuration</interface>
      </interfaces>
      <description>The security configuration.</description>
      <fields>
        <field>
          <name>version</name>
          <version>2.0.3+</version>
          <type>String</type>
          <description>The version of the model.</description>
          <required>true</required>
        </field>
        <field>
          <name>enabled</name>
          <version>2.0.3/2.0.5</version>
          <type>boolean</type>
          <description>The only mandatory element. If true, the application instance will be secured.</description>
          <required>true</required>
        </field>
        <field>
          <name>anonymousAccessEnabled</name>
          <version>2.0.3+</version>
          <type>boolean</type>
          <description>
            If enabled, the users will be able to access DAV resources unauthenticated, if Realm allows. To
            set rights for unauthenticated users, use "anonymous" username.
          </description>
          <required>true</required>
        </field>
        <field>
          <name>anonymousUsername</name>
          <version>2.0.3+</version>
          <type>String</type>
          <description>
            The username used to log in as anonymous user. The account should be enabled and existing according to
            the used JSecurity realm!
          </description>
          <required>true</required>
        </field>
        <field>
          <name>anonymousPassword</name>
          <version>2.0.3+</version>
          <type>String</type>
          <description>
            The username used to log in as anonymous user. The account should be enabled and existing according to
            the used JSecurity realm!
          </description>
          <required>true</required>
        </field>
        <field>
          <name>realms</name>
          <version>2.0.3+</version>
          <description>The list of JSecurity realms used in the application.</description>
          <association>
            <type>String</type>
            <multiplicity>*</multiplicity>
          </association>
          <required>true</required>
        </field>
        <field>
          <name>securityManager</name>
          <version>2.0.3/2.0.4</version>
          <type>String</type>
          <description>The id of a security manager to be used by default security system.</description>
          <required>true</required>
        </field>
        <field>
          <name>hashIterations</name>
          <version>2.0.4+</version>
          <type>int</type>
          <description>The id of a security manager to be used by default security system.</description>
          <required>true</required>
        </field>
      </fields>
      <codeSegments>
        <codeSegment>
          <version>2.0.3</version>
          <code><![CDATA[
    public static final String MODEL_VERSION = "2.0.3";
]]></code>
        </codeSegment>
        <codeSegment>
          <version>2.0.4</version>
          <code><![CDATA[
    public static final String MODEL_VERSION = "2.0.4";
]]></code>
        </codeSegment>
        <codeSegment>
          <version>2.0.5</version>
          <code><![CDATA[
    public static final String MODEL_VERSION = "2.0.5";
]]></code>
        </codeSegment>
        <codeSegment>
          <version>2.0.7</version>
          <code><![CDATA[
    public static final String MODEL_VERSION = "2.0.7";
]]></code>
        </codeSegment>
        <codeSegment>
          <version>2.0.8</version>
          <code><![CDATA[
    public static final String MODEL_VERSION = "2.0.8";
]]></code>
        </codeSegment>
      </codeSegments>
    </class>

  </classes>
</model>
