<?xml version="1.0" encoding="UTF-8" ?>
<!--

    Sonatype Nexus (TM) Open Source Version
    Copyright (c) 2008-present Sonatype, Inc.
    All rights reserved. Includes the third-party code listed at http://links.sonatype.com/products/nexus/oss/attributions.

    This program and the accompanying materials are made available under the terms of the Eclipse Public License Version 1.0,
    which accompanies this distribution and is available at http://www.eclipse.org/legal/epl-v10.html.

    Sonatype Nexus (TM) Professional Version is available from Sonatype, Inc. "Sonatype" and "Sonatype Nexus" are trademarks
    of Sonatype, Inc. Apache Maven is a trademark of the Apache Software Foundation. M2eclipse is a trademark of the
    Eclipse Foundation. All other trademarks are the property of their respective owners.

-->
<!DOCTYPE mapper PUBLIC "-//mybatis.org//DTD Mapper 3.0//EN" "http://mybatis.org/dtd/mybatis-3-mapper.dtd">
<mapper namespace="${namespace}">
  <insert id="createSchema">
    CREATE OR REPLACE VIEW ${format}_component_search AS
      SELECT
        c.component_id AS search_component_id,
        c.repository_id AS component_repository_id,
        c.namespace,
        c.name AS search_component_name,
        c.kind AS component_kind,
        c.version,
        c.created AS component_created,
        r.name as search_repository_name,
        b.content_type,
        b.checksums,
        a.*
      FROM ${format}_component c
       INNER JOIN ${format}_content_repository cr ON c.repository_id = cr.repository_id
       INNER JOIN repository r ON cr.config_repository_id = r.id
       INNER JOIN ${format}_asset a ON c.component_id = a.component_id
       INNER JOIN ${format}_asset_blob b ON a.asset_blob_id = b.asset_blob_id
  </insert>

  <resultMap id="searchDataMap" type="org.sonatype.nexus.repository.content.search.SearchResultData">
    <id property="componentId" column="search_component_id" />
    <result property="namespace" column="namespace"/>
    <result property="componentName" column="search_component_name"/>
    <result property="version" column="version"/>
    <result property="repositoryName" column="search_repository_name"/>
    <result property="contentType" column="content_type"/>
    <result property="checksums" column="checksums"/>
    <result property="assetId" column="asset_id"/>
    <result property="path" column="path"/>
  </resultMap>

  <select id="searchComponents" resultMap="searchDataMap">
    SELECT *
    FROM ${format}_component_search
    <where>
      <if test="filter != null"> (${filter})</if>
    </where>
    <if test="sortColumnName != null">ORDER BY (${sortColumnName}) <if test="isDescending">DESC </if></if>
    LIMIT #{limit}
    OFFSET #{offset};
  </select>

  <select id="count" resultType="int">
    SELECT COUNT(*) FROM ${format}_component_search;
  </select>
</mapper>
